gradientvis/__init__.py
gradientvis/main.py
gradientvis/methods/__init__.py
gradientvis/methods/gradcam.py
gradientvis/methods/integrated_gradients.py
gradientvis/methods/smoothgrad.py
gradientvis/utils/__init__.py
gradientvis/utils/helpers.py
gradientvis/utils/postprocessing.py
gradientvis/utils/preprocessing.py
gradientvis/visualization/__init__.py
gradientvis/visualization/heatmap.py
gradientvis/visualization/overlay.py
gradientvis-0.5.0.dist-info/METADATA
gradientvis-0.5.0.dist-info/WHEEL
gradientvis-0.5.0.dist-info/top_level.txt
gradientvis-0.5.0.dist-info/RECORD
