Metadata-Version: 2.1
Name: gradientvis
Version: 0.5.0
Summary: A library for visualizing neural network gradients
Home-page: https://github.com/desenyon/gradientvis
Author: XCALEN
Author-email: desenyon@gmail.com
Classifier: Programming Language :: Python :: 3
Classifier: License :: OSI Approved :: MIT License
Classifier: Operating System :: OS Independent
Requires-Python: >=3.6
Requires-Dist: torch
Requires-Dist: numpy
Requires-Dist: matplotlib
Requires-Dist: scipy
